netcon/netcon.m
netcon/netcon_nondisj_cpp.cpp
pynetcon/__init__.py
pynetcon/netcon.py
pynetcon-0.1.11.dist-info/METADATA
pynetcon-0.1.11.dist-info/WHEEL
pynetcon-0.1.11.dist-info/top_level.txt
pynetcon-0.1.11.dist-info/RECORD
